algopy.py
algopy-stubs/__init__.pyi
algopy-stubs/_aliases.pyi
algopy-stubs/_box.pyi
algopy-stubs/_compiled.pyi
algopy-stubs/_constants.pyi
algopy-stubs/_contract.pyi
algopy-stubs/_hints.pyi
algopy-stubs/_interfaces.pyi
algopy-stubs/_logic_sig.pyi
algopy-stubs/_native.pyi
algopy-stubs/_primitives.pyi
algopy-stubs/_reference.pyi
algopy-stubs/_state.pyi
algopy-stubs/_template_variables.pyi
algopy-stubs/_transaction.pyi
algopy-stubs/_unsigned_builtins.pyi
algopy-stubs/_util.pyi
algopy-stubs/arc4.pyi
algopy-stubs/gtxn.pyi
algopy-stubs/itxn.pyi
algopy-stubs/op.pyi
algorand_python-3.3.0.dist-info/METADATA
algorand_python-3.3.0.dist-info/WHEEL
algorand_python-3.3.0.dist-info/licenses/COPYING
algorand_python-3.3.0.dist-info/licenses/LICENSE
algorand_python-3.3.0.dist-info/RECORD
