Metadata-Version: 2.4
Name: algorand-python
Version: 3.3.0
Summary: API for writing Algorand Python Smart contracts
Author-email: Algorand Foundation <contact@algorand.foundation>
License-Expression: AGPL-3.0-or-later
License-File: COPYING
License-File: LICENSE
Classifier: Development Status :: 5 - Production/Stable
Classifier: Intended Audience :: Developers
Classifier: Typing :: Stubs Only
Requires-Python: <4,>=3.12.0
